[
  {
    "category": "Mma",
    "eventName": "Fight Nation Championship",
    "eventLogo": "http://api.sofascore.com/api/v1/unique-tournament/20463/image/dark",
    "date": "06/09/2025",
    "time": "16:00:00",
    "teamA": {
      "name": "Marko Ančić",
      "flag": "https://img.sofascore.com/api/v1/team/853562/image"
    },
    "teamB": {
      "name": "Mykola Kazachynskyi",
      "flag": "https://img.sofascore.com/api/v1/team/1112483/image"
    },
    "status": "Not started",
    "matchId": 14313850,
    "tournamentId": 20463,
    "homeTeamId": 853562,
    "awayTeamId": 1112483
  },
  {
    "category": "Mma",
    "eventName": "Fight Nation Championship",
    "eventLogo": "http://api.sofascore.com/api/v1/unique-tournament/20463/image/dark",
    "date": "06/09/2025",
    "time": "16:00:00",
    "teamA": {
      "name": "Tiriel-Luka Abramović",
      "flag": "https://img.sofascore.com/api/v1/team/934728/image"
    },
    "teamB": {
      "name": "Patryk Grabowski",
      "flag": "https://img.sofascore.com/api/v1/team/1112484/image"
    },
    "status": "Not started",
    "matchId": 14313853,
    "tournamentId": 20463,
    "homeTeamId": 934728,
    "awayTeamId": 1112484
  },
  {
    "category": "Mma",
    "eventName": "Fight Nation Championship",
    "eventLogo": "http://api.sofascore.com/api/v1/unique-tournament/20463/image/dark",
    "date": "06/09/2025",
    "time": "18:00:00",
    "teamA": {
      "name": "Aleksandar Ilić",
      "flag": "https://img.sofascore.com/api/v1/team/471046/image"
    },
    "teamB": {
      "name": "Mario Žgela",
      "flag": "https://img.sofascore.com/api/v1/team/501954/image"
    },
    "status": "Not started",
    "matchId": 14313848,
    "tournamentId": 20463,
    "homeTeamId": 471046,
    "awayTeamId": 501954
  },
  {
    "category": "Mma",
    "eventName": "Fight Nation Championship",
    "eventLogo": "http://api.sofascore.com/api/v1/unique-tournament/20463/image/dark",
    "date": "06/09/2025",
    "time": "18:00:00",
    "teamA": {
      "name": "Filip Pejić",
      "flag": "https://img.sofascore.com/api/v1/team/472175/image"
    },
    "teamB": {
      "name": "Aleksandar Janković",
      "flag": "https://img.sofascore.com/api/v1/team/488543/image"
    },
    "status": "Not started",
    "matchId": 14313844,
    "tournamentId": 20463,
    "homeTeamId": 472175,
    "awayTeamId": 488543
  },
  {
    "category": "Mma",
    "eventName": "Fight Nation Championship",
    "eventLogo": "http://api.sofascore.com/api/v1/unique-tournament/20463/image/dark",
    "date": "06/09/2025",
    "time": "18:00:00",
    "teamA": {
      "name": "Fran Luka Đurić",
      "flag": "https://img.sofascore.com/api/v1/team/489439/image"
    },
    "teamB": {
      "name": "Stipe Brčić",
      "flag": "https://img.sofascore.com/api/v1/team/463121/image"
    },
    "status": "Not started",
    "matchId": 14313842,
    "tournamentId": 20463,
    "homeTeamId": 489439,
    "awayTeamId": 463121
  },
  {
    "category": "Mma",
    "eventName": "Fight Nation Championship",
    "eventLogo": "http://api.sofascore.com/api/v1/unique-tournament/20463/image/dark",
    "date": "06/09/2025",
    "time": "18:00:00",
    "teamA": {
      "name": "Francisco Albano Barrio",
      "flag": "https://img.sofascore.com/api/v1/team/497321/image"
    },
    "teamB": {
      "name": "Vaso Bakočević",
      "flag": "https://img.sofascore.com/api/v1/team/497322/image"
    },
    "status": "Not started",
    "matchId": 14313849,
    "tournamentId": 20463,
    "homeTeamId": 497321,
    "awayTeamId": 497322
  },
  {
    "category": "Mma",
    "eventName": "Fight Nation Championship",
    "eventLogo": "http://api.sofascore.com/api/v1/unique-tournament/20463/image/dark",
    "date": "06/09/2025",
    "time": "18:00:00",
    "teamA": {
      "name": "Ivan Sičaja",
      "flag": "https://img.sofascore.com/api/v1/team/501540/image"
    },
    "teamB": {
      "name": "Paweł Polityło",
      "flag": "https://img.sofascore.com/api/v1/team/1053347/image"
    },
    "status": "Not started",
    "matchId": 14313840,
    "tournamentId": 20463,
    "homeTeamId": 501540,
    "awayTeamId": 1053347
  },
  {
    "category": "Mma",
    "eventName": "Fight Nation Championship",
    "eventLogo": "http://api.sofascore.com/api/v1/unique-tournament/20463/image/dark",
    "date": "06/09/2025",
    "time": "18:00:00",
    "teamA": {
      "name": "Ivan Vitasović",
      "flag": "https://img.sofascore.com/api/v1/team/488540/image"
    },
    "teamB": {
      "name": "Darko Stošić",
      "flag": "https://img.sofascore.com/api/v1/team/471837/image"
    },
    "status": "Not started",
    "matchId": 14313838,
    "tournamentId": 20463,
    "homeTeamId": 488540,
    "awayTeamId": 471837
  },
  {
    "category": "Mma",
    "eventName": "Fight Nation Championship",
    "eventLogo": "http://api.sofascore.com/api/v1/unique-tournament/20463/image/dark",
    "date": "06/09/2025",
    "time": "18:00:00",
    "teamA": {
      "name": "Matej Batinić",
      "flag": "https://img.sofascore.com/api/v1/team/477636/image"
    },
    "teamB": {
      "name": "Andres Ramos",
      "flag": "https://img.sofascore.com/api/v1/team/489437/image"
    },
    "status": "Not started",
    "matchId": 14313845,
    "tournamentId": 20463,
    "homeTeamId": 477636,
    "awayTeamId": 489437
  },
  {
    "category": "Mma",
    "eventName": "Fight Nation Championship",
    "eventLogo": "http://api.sofascore.com/api/v1/unique-tournament/20463/image/dark",
    "date": "06/09/2025",
    "time": "18:00:00",
    "teamA": {
      "name": "Michał Andryszak",
      "flag": "https://img.sofascore.com/api/v1/team/470068/image"
    },
    "teamB": {
      "name": "Said Sowma",
      "flag": "https://img.sofascore.com/api/v1/team/461577/image"
    },
    "status": "Not started",
    "matchId": 14313847,
    "tournamentId": 20463,
    "homeTeamId": 470068,
    "awayTeamId": 461577
  },
  {
    "category": "Mma",
    "eventName": "Fight Nation Championship",
    "eventLogo": "http://api.sofascore.com/api/v1/unique-tournament/20463/image/dark",
    "date": "06/09/2025",
    "time": "18:00:00",
    "teamA": {
      "name": "Tomislav Spahović",
      "flag": "https://img.sofascore.com/api/v1/team/501537/image"
    },
    "teamB": {
      "name": "Artūras Kudrešovas",
      "flag": "https://img.sofascore.com/api/v1/team/831605/image"
    },
    "status": "Not started",
    "matchId": 14313846,
    "tournamentId": 20463,
    "homeTeamId": 501537,
    "awayTeamId": 831605
  },
  {
    "category": "Mma",
    "eventName": "Absolute Championship Akhmat",
    "eventLogo": "http://api.sofascore.com/api/v1/unique-tournament/20254/image/dark",
    "date": "05/09/2025",
    "time": "14:00:00",
    "teamA": {
      "name": "Abdul-Rakhman Temirov",
      "flag": "https://img.sofascore.com/api/v1/team/488420/image"
    },
    "teamB": {
      "name": "Aurel Pîrtea",
      "flag": "https://img.sofascore.com/api/v1/team/471344/image"
    },
    "status": "Not started",
    "matchId": 14552481,
    "tournamentId": 20254,
    "homeTeamId": 488420,
    "awayTeamId": 471344
  },
  {
    "category": "Mma",
    "eventName": "Absolute Championship Akhmat",
    "eventLogo": "http://api.sofascore.com/api/v1/unique-tournament/20254/image/dark",
    "date": "05/09/2025",
    "time": "14:00:00",
    "teamA": {
      "name": "Adam Bogatyrev",
      "flag": "https://img.sofascore.com/api/v1/team/508240/image"
    },
    "teamB": {
      "name": "Klidson Abreu",
      "flag": "https://img.sofascore.com/api/v1/team/473007/image"
    },
    "status": "Not started",
    "matchId": 14552479,
    "tournamentId": 20254,
    "homeTeamId": 508240,
    "awayTeamId": 473007
  },
  {
    "category": "Mma",
    "eventName": "Absolute Championship Akhmat",
    "eventLogo": "http://api.sofascore.com/api/v1/unique-tournament/20254/image/dark",
    "date": "05/09/2025",
    "time": "14:00:00",
    "teamA": {
      "name": "Amazasp Martirosyan",
      "flag": "https://img.sofascore.com/api/v1/team/488423/image"
    },
    "teamB": {
      "name": "Herbert Batista",
      "flag": "https://img.sofascore.com/api/v1/team/476430/image"
    },
    "status": "Not started",
    "matchId": 14552476,
    "tournamentId": 20254,
    "homeTeamId": 488423,
    "awayTeamId": 476430
  },
  {
    "category": "Mma",
    "eventName": "Absolute Championship Akhmat",
    "eventLogo": "http://api.sofascore.com/api/v1/unique-tournament/20254/image/dark",
    "date": "05/09/2025",
    "time": "14:00:00",
    "teamA": {
      "name": "Charles Henrique",
      "flag": "https://img.sofascore.com/api/v1/team/478706/image"
    },
    "teamB": {
      "name": "Ayk Kazaryan",
      "flag": "https://img.sofascore.com/api/v1/team/471358/image"
    },
    "status": "Not started",
    "matchId": 14552480,
    "tournamentId": 20254,
    "homeTeamId": 478706,
    "awayTeamId": 471358
  },
  {
    "category": "Mma",
    "eventName": "Absolute Championship Akhmat",
    "eventLogo": "http://api.sofascore.com/api/v1/unique-tournament/20254/image/dark",
    "date": "05/09/2025",
    "time": "14:00:00",
    "teamA": {
      "name": "Islam Meshev",
      "flag": "https://img.sofascore.com/api/v1/team/488424/image"
    },
    "teamB": {
      "name": "Gegam Manavazyan",
      "flag": "https://img.sofascore.com/api/v1/team/1101193/image"
    },
    "status": "Not started",
    "matchId": 14552478,
    "tournamentId": 20254,
    "homeTeamId": 488424,
    "awayTeamId": 1101193
  },
  {
    "category": "Mma",
    "eventName": "Absolute Championship Akhmat",
    "eventLogo": "http://api.sofascore.com/api/v1/unique-tournament/20254/image/dark",
    "date": "05/09/2025",
    "time": "14:00:00",
    "teamA": {
      "name": "Manas Temirbekov",
      "flag": "https://img.sofascore.com/api/v1/team/854639/image"
    },
    "teamB": {
      "name": "Sergey Starodub",
      "flag": "https://img.sofascore.com/api/v1/team/492431/image"
    },
    "status": "Not started",
    "matchId": 14552470,
    "tournamentId": 20254,
    "homeTeamId": 854639,
    "awayTeamId": 492431
  },
  {
    "category": "Mma",
    "eventName": "Absolute Championship Akhmat",
    "eventLogo": "http://api.sofascore.com/api/v1/unique-tournament/20254/image/dark",
    "date": "05/09/2025",
    "time": "14:00:00",
    "teamA": {
      "name": "Radjab Ramazanov",
      "flag": "https://img.sofascore.com/api/v1/team/521794/image"
    },
    "teamB": {
      "name": "Tamerlan Kulaev",
      "flag": "https://img.sofascore.com/api/v1/team/477101/image"
    },
    "status": "Not started",
    "matchId": 14552474,
    "tournamentId": 20254,
    "homeTeamId": 521794,
    "awayTeamId": 477101
  },
  {
    "category": "Mma",
    "eventName": "Absolute Championship Akhmat",
    "eventLogo": "http://api.sofascore.com/api/v1/unique-tournament/20254/image/dark",
    "date": "05/09/2025",
    "time": "14:00:00",
    "teamA": {
      "name": "Tamerlan Temirov",
      "flag": "https://img.sofascore.com/api/v1/team/1107348/image"
    },
    "teamB": {
      "name": "Vadim Ogar",
      "flag": "https://img.sofascore.com/api/v1/team/474612/image"
    },
    "status": "Not started",
    "matchId": 14552472,
    "tournamentId": 20254,
    "homeTeamId": 1107348,
    "awayTeamId": 474612
  },
  {
    "category": "Mma",
    "eventName": "Absolute Championship Akhmat",
    "eventLogo": "http://api.sofascore.com/api/v1/unique-tournament/20254/image/dark",
    "date": "05/09/2025",
    "time": "14:00:00",
    "teamA": {
      "name": "Viskhan Kadirov",
      "flag": "https://img.sofascore.com/api/v1/team/931013/image"
    },
    "teamB": {
      "name": "Luis Rafael Laurentino",
      "flag": "https://img.sofascore.com/api/v1/team/473185/image"
    },
    "status": "Not started",
    "matchId": 14552468,
    "tournamentId": 20254,
    "homeTeamId": 931013,
    "awayTeamId": 473185
  },
  {
    "category": "Mma",
    "eventName": "Absolute Championship Akhmat",
    "eventLogo": "http://api.sofascore.com/api/v1/unique-tournament/20254/image/dark",
    "date": "05/09/2025",
    "time": "16:00:00",
    "teamA": {
      "name": "Elias Silvério",
      "flag": "https://img.sofascore.com/api/v1/team/480237/image"
    },
    "teamB": {
      "name": "Andrey Koshkin",
      "flag": "https://img.sofascore.com/api/v1/team/471212/image"
    },
    "status": "Not started",
    "matchId": 14552475,
    "tournamentId": 20254,
    "homeTeamId": 480237,
    "awayTeamId": 471212
  },
  {
    "category": "Mma",
    "eventName": "Absolute Championship Akhmat",
    "eventLogo": "http://api.sofascore.com/api/v1/unique-tournament/20254/image/dark",
    "date": "05/09/2025",
    "time": "16:00:00",
    "teamA": {
      "name": "Mukhamed Kokov",
      "flag": "https://img.sofascore.com/api/v1/team/492489/image"
    },
    "teamB": {
      "name": "Davi Ramos",
      "flag": "https://img.sofascore.com/api/v1/team/471849/image"
    },
    "status": "Not started",
    "matchId": 14552473,
    "tournamentId": 20254,
    "homeTeamId": 492489,
    "awayTeamId": 471849
  },
  {
    "category": "Mma",
    "eventName": "Absolute Championship Akhmat",
    "eventLogo": "http://api.sofascore.com/api/v1/unique-tournament/20254/image/dark",
    "date": "05/09/2025",
    "time": "16:00:00",
    "teamA": {
      "name": "Nikola Dipchikov",
      "flag": "https://img.sofascore.com/api/v1/team/473697/image"
    },
    "teamB": {
      "name": "Ibragim Magomedov",
      "flag": "https://img.sofascore.com/api/v1/team/461279/image"
    },
    "status": "Not started",
    "matchId": 14552477,
    "tournamentId": 20254,
    "homeTeamId": 473697,
    "awayTeamId": 461279
  },
  {
    "category": "Mma",
    "eventName": "Absolute Championship Akhmat",
    "eventLogo": "http://api.sofascore.com/api/v1/unique-tournament/20254/image/dark",
    "date": "05/09/2025",
    "time": "16:00:00",
    "teamA": {
      "name": "Ramazan Emeev",
      "flag": "https://img.sofascore.com/api/v1/team/473928/image"
    },
    "teamB": {
      "name": "Artem Frolov",
      "flag": "https://img.sofascore.com/api/v1/team/476439/image"
    },
    "status": "Not started",
    "matchId": 14552471,
    "tournamentId": 20254,
    "homeTeamId": 473928,
    "awayTeamId": 476439
  },
  {
    "category": "Mma",
    "eventName": "Absolute Championship Akhmat",
    "eventLogo": "http://api.sofascore.com/api/v1/unique-tournament/20254/image/dark",
    "date": "05/09/2025",
    "time": "16:00:00",
    "teamA": {
      "name": "Vinicius Cruz",
      "flag": "https://img.sofascore.com/api/v1/team/474664/image"
    },
    "teamB": {
      "name": "Albert Tumenov",
      "flag": "https://img.sofascore.com/api/v1/team/471031/image"
    },
    "status": "Not started",
    "matchId": 14552469,
    "tournamentId": 20254,
    "homeTeamId": 474664,
    "awayTeamId": 471031
  },
  {
    "category": "Mma",
    "eventName": "Matchroom Boxing",
    "eventLogo": "http://api.sofascore.com/api/v1/unique-tournament/20256/image/dark",
    "date": "07/09/2025",
    "time": "04:00:00",
    "teamA": {
      "name": "Angel Patrón",
      "flag": "https://img.sofascore.com/api/v1/team/1124082/image"
    },
    "teamB": {
      "name": "Carlos Vargas",
      "flag": "https://img.sofascore.com/api/v1/team/1124083/image"
    },
    "status": "Not started",
    "matchId": 14598881,
    "tournamentId": 20256,
    "homeTeamId": 1124082,
    "awayTeamId": 1124083
  },
  {
    "category": "Mma",
    "eventName": "Matchroom Boxing",
    "eventLogo": "http://api.sofascore.com/api/v1/unique-tournament/20256/image/dark",
    "date": "07/09/2025",
    "time": "04:00:00",
    "teamA": {
      "name": "Israel Ramirez",
      "flag": "https://img.sofascore.com/api/v1/team/1124084/image"
    },
    "teamB": {
      "name": "Jose Amaro",
      "flag": "https://img.sofascore.com/api/v1/team/1124081/image"
    },
    "status": "Not started",
    "matchId": 14598880,
    "tournamentId": 20256,
    "homeTeamId": 1124084,
    "awayTeamId": 1124081
  },
  {
    "category": "Mma",
    "eventName": "Matchroom Boxing",
    "eventLogo": "http://api.sofascore.com/api/v1/unique-tournament/20256/image/dark",
    "date": "07/09/2025",
    "time": "04:00:00",
    "teamA": {
      "name": "Luis Corona Parra",
      "flag": "https://img.sofascore.com/api/v1/team/1124087/image"
    },
    "teamB": {
      "name": "Yohan Orduño",
      "flag": "https://img.sofascore.com/api/v1/team/1124088/image"
    },
    "status": "Not started",
    "matchId": 14598883,
    "tournamentId": 20256,
    "homeTeamId": 1124087,
    "awayTeamId": 1124088
  },
  {
    "category": "Mma",
    "eventName": "Matchroom Boxing",
    "eventLogo": "http://api.sofascore.com/api/v1/unique-tournament/20256/image/dark",
    "date": "07/09/2025",
    "time": "04:00:00",
    "teamA": {
      "name": "Oscar Valdez",
      "flag": "https://img.sofascore.com/api/v1/team/529400/image"
    },
    "teamB": {
      "name": "Ricky Medina",
      "flag": "https://img.sofascore.com/api/v1/team/1124080/image"
    },
    "status": "Not started",
    "matchId": 14598879,
    "tournamentId": 20256,
    "homeTeamId": 529400,
    "awayTeamId": 1124080
  },
  {
    "category": "Mma",
    "eventName": "Matchroom Boxing",
    "eventLogo": "http://api.sofascore.com/api/v1/unique-tournament/20256/image/dark",
    "date": "07/09/2025",
    "time": "04:00:00",
    "teamA": {
      "name": "Ricardo Gonzalez",
      "flag": "https://img.sofascore.com/api/v1/team/1124085/image"
    },
    "teamB": {
      "name": "Leonardo Quintana",
      "flag": "https://img.sofascore.com/api/v1/team/1124086/image"
    },
    "status": "Not started",
    "matchId": 14598882,
    "tournamentId": 20256,
    "homeTeamId": 1124085,
    "awayTeamId": 1124086
  },
  {
    "category": "Mma",
    "eventName": "UFC",
    "eventLogo": "http://api.sofascore.com/api/v1/unique-tournament/19906/image/dark",
    "date": "06/09/2025",
    "time": "16:00:00",
    "teamA": {
      "name": "Axel Sola",
      "flag": "https://img.sofascore.com/api/v1/team/471353/image"
    },
    "teamB": {
      "name": "Rhys McKee",
      "flag": "https://img.sofascore.com/api/v1/team/461365/image"
    },
    "status": "Not started",
    "matchId": 14567269,
    "tournamentId": 19906,
    "homeTeamId": 471353,
    "awayTeamId": 461365
  },
  {
    "category": "Mma",
    "eventName": "UFC",
    "eventLogo": "http://api.sofascore.com/api/v1/unique-tournament/19906/image/dark",
    "date": "06/09/2025",
    "time": "16:00:00",
    "teamA": {
      "name": "Brad Tavares",
      "flag": "https://img.sofascore.com/api/v1/team/469960/image"
    },
    "teamB": {
      "name": "Robert Bryczek",
      "flag": "https://img.sofascore.com/api/v1/team/505215/image"
    },
    "status": "Not started",
    "matchId": 14495947,
    "tournamentId": 19906,
    "homeTeamId": 469960,
    "awayTeamId": 505215
  },
  {
    "category": "Mma",
    "eventName": "UFC",
    "eventLogo": "http://api.sofascore.com/api/v1/unique-tournament/19906/image/dark",
    "date": "06/09/2025",
    "time": "16:00:00",
    "teamA": {
      "name": "Marcin Tybura",
      "flag": "https://img.sofascore.com/api/v1/team/461550/image"
    },
    "teamB": {
      "name": "Ante Delija",
      "flag": "https://img.sofascore.com/api/v1/team/461644/image"
    },
    "status": "Not started",
    "matchId": 14095576,
    "tournamentId": 19906,
    "homeTeamId": 461550,
    "awayTeamId": 461644
  },
  {
    "category": "Mma",
    "eventName": "UFC",
    "eventLogo": "http://api.sofascore.com/api/v1/unique-tournament/19906/image/dark",
    "date": "06/09/2025",
    "time": "16:00:00",
    "teamA": {
      "name": "Oumar Sy",
      "flag": "https://img.sofascore.com/api/v1/team/516551/image"
    },
    "teamB": {
      "name": "Brendson Ribeiro",
      "flag": "https://img.sofascore.com/api/v1/team/489430/image"
    },
    "status": "Not started",
    "matchId": 14095579,
    "tournamentId": 19906,
    "homeTeamId": 516551,
    "awayTeamId": 489430
  },
  {
    "category": "Mma",
    "eventName": "UFC",
    "eventLogo": "http://api.sofascore.com/api/v1/unique-tournament/19906/image/dark",
    "date": "06/09/2025",
    "time": "16:00:00",
    "teamA": {
      "name": "Rinat Fakhretdinov",
      "flag": "https://img.sofascore.com/api/v1/team/461848/image"
    },
    "teamB": {
      "name": "Andreas Gustafsson",
      "flag": "https://img.sofascore.com/api/v1/team/471192/image"
    },
    "status": "Not started",
    "matchId": 14095578,
    "tournamentId": 19906,
    "homeTeamId": 461848,
    "awayTeamId": 471192
  },
  {
    "category": "Mma",
    "eventName": "UFC",
    "eventLogo": "http://api.sofascore.com/api/v1/unique-tournament/19906/image/dark",
    "date": "06/09/2025",
    "time": "16:00:00",
    "teamA": {
      "name": "Sam Patterson",
      "flag": "https://img.sofascore.com/api/v1/team/466912/image"
    },
    "teamB": {
      "name": "Trey Waters",
      "flag": "https://img.sofascore.com/api/v1/team/474567/image"
    },
    "status": "Not started",
    "matchId": 14495946,
    "tournamentId": 19906,
    "homeTeamId": 466912,
    "awayTeamId": 474567
  },
  {
    "category": "Mma",
    "eventName": "UFC",
    "eventLogo": "http://api.sofascore.com/api/v1/unique-tournament/19906/image/dark",
    "date": "06/09/2025",
    "time": "16:00:00",
    "teamA": {
      "name": "Shauna Bannon",
      "flag": "https://img.sofascore.com/api/v1/team/482995/image"
    },
    "teamB": {
      "name": "Sam Hughes",
      "flag": "https://img.sofascore.com/api/v1/team/470059/image"
    },
    "status": "Not started",
    "matchId": 14095580,
    "tournamentId": 19906,
    "homeTeamId": 482995,
    "awayTeamId": 470059
  },
  {
    "category": "Mma",
    "eventName": "UFC",
    "eventLogo": "http://api.sofascore.com/api/v1/unique-tournament/19906/image/dark",
    "date": "06/09/2025",
    "time": "16:00:00",
    "teamA": {
      "name": "William Gomis",
      "flag": "https://img.sofascore.com/api/v1/team/469975/image"
    },
    "teamB": {
      "name": "Robert Ruchała",
      "flag": "https://img.sofascore.com/api/v1/team/463055/image"
    },
    "status": "Not started",
    "matchId": 14495945,
    "tournamentId": 19906,
    "homeTeamId": 469975,
    "awayTeamId": 463055
  },
  {
    "category": "Mma",
    "eventName": "UFC",
    "eventLogo": "http://api.sofascore.com/api/v1/unique-tournament/19906/image/dark",
    "date": "06/09/2025",
    "time": "18:00:00",
    "teamA": {
      "name": "Benoit Saint-Denis",
      "flag": "https://img.sofascore.com/api/v1/team/461588/image"
    },
    "teamB": {
      "name": "Mauricio Ruffy",
      "flag": "https://img.sofascore.com/api/v1/team/493397/image"
    },
    "status": "Not started",
    "matchId": 14495941,
    "tournamentId": 19906,
    "homeTeamId": 461588,
    "awayTeamId": 493397
  },
  {
    "category": "Mma",
    "eventName": "UFC",
    "eventLogo": "http://api.sofascore.com/api/v1/unique-tournament/19906/image/dark",
    "date": "06/09/2025",
    "time": "18:00:00",
    "teamA": {
      "name": "Bolaji Oki",
      "flag": "https://img.sofascore.com/api/v1/team/486845/image"
    },
    "teamB": {
      "name": "Mason Jones",
      "flag": "https://img.sofascore.com/api/v1/team/461473/image"
    },
    "status": "Not started",
    "matchId": 14095577,
    "tournamentId": 19906,
    "homeTeamId": 486845,
    "awayTeamId": 461473
  },
  {
    "category": "Mma",
    "eventName": "UFC",
    "eventLogo": "http://api.sofascore.com/api/v1/unique-tournament/19906/image/dark",
    "date": "06/09/2025",
    "time": "18:00:00",
    "teamA": {
      "name": "Farès Ziam",
      "flag": "https://img.sofascore.com/api/v1/team/461590/image"
    },
    "teamB": {
      "name": "Kauê Fernandes",
      "flag": "https://img.sofascore.com/api/v1/team/497331/image"
    },
    "status": "Not started",
    "matchId": 14495943,
    "tournamentId": 19906,
    "homeTeamId": 461590,
    "awayTeamId": 497331
  },
  {
    "category": "Mma",
    "eventName": "UFC",
    "eventLogo": "http://api.sofascore.com/api/v1/unique-tournament/19906/image/dark",
    "date": "06/09/2025",
    "time": "18:00:00",
    "teamA": {
      "name": "Modestas Bukauskas",
      "flag": "https://img.sofascore.com/api/v1/team/461837/image"
    },
    "teamB": {
      "name": "Paul Craig",
      "flag": "https://img.sofascore.com/api/v1/team/461475/image"
    },
    "status": "Not started",
    "matchId": 14495942,
    "tournamentId": 19906,
    "homeTeamId": 461837,
    "awayTeamId": 461475
  },
  {
    "category": "Mma",
    "eventName": "UFC",
    "eventLogo": "http://api.sofascore.com/api/v1/unique-tournament/19906/image/dark",
    "date": "06/09/2025",
    "time": "18:00:00",
    "teamA": {
      "name": "Nassourdine Imavov",
      "flag": "https://img.sofascore.com/api/v1/team/461598/image"
    },
    "teamB": {
      "name": "Caio Borralho",
      "flag": "https://img.sofascore.com/api/v1/team/461771/image"
    },
    "status": "Not started",
    "matchId": 14095574,
    "tournamentId": 19906,
    "homeTeamId": 461598,
    "awayTeamId": 461771
  },
  {
    "category": "Mma",
    "eventName": "UFC",
    "eventLogo": "http://api.sofascore.com/api/v1/unique-tournament/19906/image/dark",
    "date": "06/09/2025",
    "time": "18:00:00",
    "teamA": {
      "name": "Patricio Pitbull",
      "flag": "https://img.sofascore.com/api/v1/team/461806/image"
    },
    "teamB": {
      "name": "Losene Keita",
      "flag": "https://img.sofascore.com/api/v1/team/518562/image"
    },
    "status": "Not started",
    "matchId": 14495944,
    "tournamentId": 19906,
    "homeTeamId": 461806,
    "awayTeamId": 518562
  },
  {
    "category": "Mma",
    "eventName": "Dana White's Contender Series",
    "eventLogo": "http://api.sofascore.com/api/v1/unique-tournament/20264/image/dark",
    "date": "03/09/2025",
    "time": "02:00:00",
    "teamA": {
      "name": "Eduardo Henrique",
      "flag": "https://img.sofascore.com/api/v1/team/1121499/image"
    },
    "teamB": {
      "name": "An Tuan Ho",
      "flag": "https://img.sofascore.com/api/v1/team/531600/image"
    },
    "status": "Not started",
    "matchId": 14557373,
    "tournamentId": 20264,
    "homeTeamId": 1121499,
    "awayTeamId": 531600
  },
  {
    "category": "Mma",
    "eventName": "Dana White's Contender Series",
    "eventLogo": "http://api.sofascore.com/api/v1/unique-tournament/20264/image/dark",
    "date": "03/09/2025",
    "time": "02:00:00",
    "teamA": {
      "name": "Jack Congdon",
      "flag": "https://img.sofascore.com/api/v1/team/1120908/image"
    },
    "teamB": {
      "name": "Jean-Paul Lebosnoyani",
      "flag": "https://img.sofascore.com/api/v1/team/1120910/image"
    },
    "status": "Not started",
    "matchId": 14557372,
    "tournamentId": 20264,
    "homeTeamId": 1120908,
    "awayTeamId": 1120910
  },
  {
    "category": "Mma",
    "eventName": "Dana White's Contender Series",
    "eventLogo": "http://api.sofascore.com/api/v1/unique-tournament/20264/image/dark",
    "date": "03/09/2025",
    "time": "02:00:00",
    "teamA": {
      "name": "Mandel Nallo",
      "flag": "https://img.sofascore.com/api/v1/team/461321/image"
    },
    "teamB": {
      "name": "Samuel Silva",
      "flag": "https://img.sofascore.com/api/v1/team/1081843/image"
    },
    "status": "Not started",
    "matchId": 14557365,
    "tournamentId": 20264,
    "homeTeamId": 461321,
    "awayTeamId": 1081843
  },
  {
    "category": "Mma",
    "eventName": "Dana White's Contender Series",
    "eventLogo": "http://api.sofascore.com/api/v1/unique-tournament/20264/image/dark",
    "date": "03/09/2025",
    "time": "02:00:00",
    "teamA": {
      "name": "Theo Haig",
      "flag": "https://img.sofascore.com/api/v1/team/465940/image"
    },
    "teamB": {
      "name": "Cezary Oleksiejczuk",
      "flag": "https://img.sofascore.com/api/v1/team/1076252/image"
    },
    "status": "Not started",
    "matchId": 14557367,
    "tournamentId": 20264,
    "homeTeamId": 465940,
    "awayTeamId": 1076252
  },
  {
    "category": "Mma",
    "eventName": "Dana White's Contender Series",
    "eventLogo": "http://api.sofascore.com/api/v1/unique-tournament/20264/image/dark",
    "date": "03/09/2025",
    "time": "02:00:00",
    "teamA": {
      "name": "Tommy McMillen",
      "flag": "https://img.sofascore.com/api/v1/team/801211/image"
    },
    "teamB": {
      "name": "David Mgoyan",
      "flag": "https://img.sofascore.com/api/v1/team/1120906/image"
    },
    "status": "Not started",
    "matchId": 14567267,
    "tournamentId": 20264,
    "homeTeamId": 801211,
    "awayTeamId": 1120906
  }
]